meter_digits_recognizer/__init__.py
meter_digits_recognizer/_meter_digits_recognizer.py
meter_digits_recognizer/_net.py
meter_digits_recognizer/model_weights.pt
meter_digits_recognizer-0.1.6.dist-info/METADATA
meter_digits_recognizer-0.1.6.dist-info/WHEEL
meter_digits_recognizer-0.1.6.dist-info/top_level.txt
meter_digits_recognizer-0.1.6.dist-info/RECORD
