Metadata-Version: 2.1
Name: meter-digits-recognizer
Version: 0.1.6
Summary: UNKNOWN
Home-page: https://github.com/ardiloot/meter-digits-recognizer
Author: Ardi Loot
Author-email: ardi.loot@outlook.com
License: UNKNOWN
Platform: UNKNOWN
Requires-Dist: Pillow
Requires-Dist: opencv-python
